{"node_name": "root", "test_feature": "age", "success_features": [1, 2, 3], "fail_features": [4, 5, 6], "yes_child": {"node_name": "node1", "test_feature": "thal", "success_features": ["a", "b", "c"], "fail_features": ["d"], "yes_child": {"node_name": "leaf1", "class": 1}, "no_child": {"node_name": "leaf2", "class": 0}}, "no_child": {"node_name": "node2", "test_feature": "sex", "success_features": ["thalach"], "fail_features": ["fbs"], "yes_child": {"node_name": "leaf3", "class": 0}, "no_child": {"node_name": "leaf4", "class": 1}}}